ajenti_plugin_cpu_temp_widget/.gitignore
ajenti_plugin_cpu_temp_widget/README.md
ajenti_plugin_cpu_temp_widget/__init__.py
ajenti_plugin_cpu_temp_widget/plugin.yml
ajenti_plugin_cpu_temp_widget/views.py
ajenti_plugin_cpu_temp_widget/widget.py
ajenti_plugin_cpu_temp_widget/resources/build/all.css
ajenti_plugin_cpu_temp_widget/resources/build/all.js
ajenti_plugin_cpu_temp_widget/resources/build/all.vendor.css
ajenti_plugin_cpu_temp_widget/resources/build/all.vendor.js
ajenti_plugin_cpu_temp_widget/resources/js/module.coffee
ajenti_plugin_cpu_temp_widget/resources/js/controllers/widget.controller.coffee
ajenti_plugin_cpu_temp_widget/resources/partial/widget.config.html
ajenti_plugin_cpu_temp_widget/resources/partial/widget.html
ajenti.plugin.cpu_temp_widget-0.1.dist-info/METADATA
ajenti.plugin.cpu_temp_widget-0.1.dist-info/WHEEL
ajenti.plugin.cpu_temp_widget-0.1.dist-info/top_level.txt
ajenti.plugin.cpu_temp_widget-0.1.dist-info/RECORD
