Metadata-Version: 2.1
Name: ajenti.plugin.cpu-temp-widget
Version: 0.1
Summary: CPU Temp widget
Home-page: https://yuriyyurinskiy.ru
Author: Yuriy Yurinskiy
Author-email: yuriyyurinskiy@yandex.ru
License: UNKNOWN
Platform: UNKNOWN
Requires-Dist: aj
Requires-Dist: ajenti.plugin.core
